remerge/__init__.py
remerge/core.py
remerge_mwe-0.2.1.dist-info/LICENSE
remerge_mwe-0.2.1.dist-info/WHEEL
remerge_mwe-0.2.1.dist-info/METADATA
remerge_mwe-0.2.1.dist-info/RECORD
