Metadata-Version: 2.1
Name: remerge-mwe
Version: 0.2.1
Summary: REMERGE is a Multi-Word Expression (MWE) discovery algorithm derived from the MERGE algorithm.
License: MIT
Author: Peter Baumgartner
Author-email: 5107405+pmbaumgartner@users.noreply.github.com
Requires-Python: >=3.8,<4.0
Classifier: License :: OSI Approved :: MIT License
Classifier: Programming Language :: Python :: 3
Classifier: Programming Language :: Python :: 3.8
Classifier: Programming Language :: Python :: 3.9
Classifier: Programming Language :: Python :: 3.10
Requires-Dist: numpy (>=1.18,<1.23)
Requires-Dist: tqdm (>=4.64.1,<5.0.0)
